AcDummyLib/__init__.py
AcDummyLib/ac.py
ac/__init__.py
AcDummyLib-0.2.0.dist-info/LICENSE
AcDummyLib-0.2.0.dist-info/METADATA
AcDummyLib-0.2.0.dist-info/WHEEL
AcDummyLib-0.2.0.dist-info/top_level.txt
AcDummyLib-0.2.0.dist-info/RECORD
